modalfold/__init__.py
modalfold/base.py
modalfold/constants.py
modalfold/convert.py
modalfold/esm2.py
modalfold/esmfold.py
modalfold/utils.py
modalfold/images/__init__.py
modalfold/images/esm.py
modalfold/images/volumes.py
modalfold-0.0.13.dist-info/METADATA
modalfold-0.0.13.dist-info/WHEEL
modalfold-0.0.13.dist-info/licenses/LICENSE
modalfold-0.0.13.dist-info/RECORD
