Metadata-Version: 2.4
Name: modalfold
Version: 0.0.13
Summary: A protein structure prediction package
Project-URL: Homepage, https://github.com/jakublala/modalfold
Author-email: Jakub Lála <jakublala@gmail.com>
License-File: LICENSE
Classifier: License :: OSI Approved :: MIT License
Classifier: Operating System :: OS Independent
Classifier: Programming Language :: Python :: 3
Requires-Python: >=3.12
Requires-Dist: biotite>=1.0.1
Requires-Dist: deprecated>=1.2.14
Requires-Dist: modal>=0.73.12
Requires-Dist: numpy>=2.2.2
Requires-Dist: pre-commit>=4.1.0
Requires-Dist: pytest-mock>=3.14.0
Requires-Dist: pytest-xdist>=3.6.1
Requires-Dist: pytest>=8.3.4
Requires-Dist: torch>=2.5.1
